_kaldi_native_fbank.cp313-win32.pyd
kaldi-native-fbank-core.dll
kaldi-native-fbank-core.lib
kaldi_native_fbank/__init__.py
kaldi_native_fbank/__init__.pyi
kaldi_native_fbank/include/kaldi-native-fbank/csrc/feature-fbank.h
kaldi_native_fbank/include/kaldi-native-fbank/csrc/feature-functions.h
kaldi_native_fbank/include/kaldi-native-fbank/csrc/feature-mfcc.h
kaldi_native_fbank/include/kaldi-native-fbank/csrc/feature-raw-audio-samples.h
kaldi_native_fbank/include/kaldi-native-fbank/csrc/feature-window.h
kaldi_native_fbank/include/kaldi-native-fbank/csrc/istft.h
kaldi_native_fbank/include/kaldi-native-fbank/csrc/kaldi-math.h
kaldi_native_fbank/include/kaldi-native-fbank/csrc/log.h
kaldi_native_fbank/include/kaldi-native-fbank/csrc/mel-computations.h
kaldi_native_fbank/include/kaldi-native-fbank/csrc/online-feature.h
kaldi_native_fbank/include/kaldi-native-fbank/csrc/rfft.h
kaldi_native_fbank/include/kaldi-native-fbank/csrc/stft.h
kaldi_native_fbank/include/kaldi-native-fbank/csrc/whisper-feature.h
kaldi_native_fbank/lib/kaldi-native-fbank-core.dll
kaldi_native_fbank/lib/kaldi-native-fbank-core.lib
kaldi_native_fbank-1.22.3.dist-info/licenses/LICENSE
kaldi_native_fbank-1.22.3.dist-info/METADATA
kaldi_native_fbank-1.22.3.dist-info/WHEEL
kaldi_native_fbank-1.22.3.dist-info/top_level.txt
kaldi_native_fbank-1.22.3.dist-info/RECORD
