Metadata-Version: 2.1
Name: kaldi-native-fbank
Version: 1.22.3
Summary: UNKNOWN
Home-page: https://github.com/csukuangfj/kaldi-native-fbank
Author: Fangjun Kuang
Author-email: csukuangfj@gmail.com
License: Apache-2.0
Platform: UNKNOWN
Classifier: Programming Language :: C++
Classifier: Programming Language :: Python
Classifier: Programming Language :: Python :: 3
Classifier: Topic :: Scientific/Engineering :: Artificial Intelligence
Requires-Python: >=3.8.0
License-File: LICENSE
